<annotation>
	<folder>nomask</folder>
	<filename>nomask_29.jpg</filename>
	<path>D:\PycharmProject(D)\kz_demo\preData\nomask\nomask_29.jpg</path>
	<source>
		<database>Unknown</database>
	</source>
	<size>
		<width>800</width>
		<height>500</height>
		<depth>1</depth>
	</size>
	<segmented>0</segmented>
	<object>
		<name>nomask</name>
		<pose>Unspecified</pose>
		<truncated>0</truncated>
		<difficult>0</difficult>
		<bndbox>
			<xmin>414</xmin>
			<ymin>50</ymin>
			<xmax>552</xmax>
			<ymax>444</ymax>
		</bndbox>
	</object>
</annotation>
